flytekitplugins_awssagemaker-1.16.12-py3.14-nspkg.pth
flytekitplugins/awssagemaker_inference/__init__.py
flytekitplugins/awssagemaker_inference/boto3_connector.py
flytekitplugins/awssagemaker_inference/boto3_mixin.py
flytekitplugins/awssagemaker_inference/boto3_task.py
flytekitplugins/awssagemaker_inference/connector.py
flytekitplugins/awssagemaker_inference/task.py
flytekitplugins/awssagemaker_inference/workflow.py
flytekitplugins_awssagemaker-1.16.12.dist-info/METADATA
flytekitplugins_awssagemaker-1.16.12.dist-info/WHEEL
flytekitplugins_awssagemaker-1.16.12.dist-info/entry_points.txt
flytekitplugins_awssagemaker-1.16.12.dist-info/namespace_packages.txt
flytekitplugins_awssagemaker-1.16.12.dist-info/top_level.txt
flytekitplugins_awssagemaker-1.16.12.dist-info/RECORD
